henhoe2vec/__init__.py
henhoe2vec/__main__.py
henhoe2vec/alias_sampling.py
henhoe2vec/embeddings.py
henhoe2vec/henhoe2vec.py
henhoe2vec/henhoe2vec_walks.py
henhoe2vec/napkin.py
henhoe2vec/utils.py
henhoe2vec-1.0.4.dist-info/LICENSE.txt
henhoe2vec-1.0.4.dist-info/METADATA
henhoe2vec-1.0.4.dist-info/WHEEL
henhoe2vec-1.0.4.dist-info/top_level.txt
henhoe2vec-1.0.4.dist-info/RECORD
