Metadata-Version: 2.1
Name: henhoe2vec
Version: 1.0.4
Summary: Implementation of the HeNHoE-2vec algorithm by Valentini et al. (2021).
Author-email: Robert Giesler <robert.giesler@rwth-aachen.de>
License: MIT License
Project-URL: Repository, https://github.com/RobertGiesler/HeNHoE-2vec
Keywords: embeddings,graph embeddings,network embeddings,node embeddings,multilayer graph embeddings,multilayer network embeddings,node2vec,HeNHoE-2vec,Het-node2vec,multilayer networks
Classifier: Programming Language :: Python :: 3
Classifier: Programming Language :: Python :: 3.8
Classifier: Programming Language :: Python :: 3.9
Classifier: Programming Language :: Python :: 3.10
Classifier: Programming Language :: Python :: 3.11
Classifier: License :: OSI Approved :: MIT License
Classifier: Operating System :: OS Independent
Requires-Python: >=3.8
License-File: LICENSE.txt
Requires-Dist: pandas >=1.2.0
Requires-Dist: numpy >=1.22.0
Requires-Dist: networkx >=2.5
Requires-Dist: gensim >=4.3.0
Provides-Extra: dev
Requires-Dist: pytest ; extra == 'dev'
Requires-Dist: build ; extra == 'dev'
